[
  {
    "position": 1,
    "is_sold": false,
    "sold_to": {},
    "serial": "658c4b88fc13ae0367fa21eb"
  },
  {
    "position": 2,
    "is_sold": true,
    "sold_to": {},
    "serial": "658c4b88fc13ae0367fa21ec"
  },
  {
    "position": 3,
    "is_sold": true,
    "sold_to": {},
    "serial": "658c4b88fc13ae0367fa21ed"
  },
  {
    "position": 4,
    "is_sold": true,
    "sold_to": {},
    "serial": "658c4b88fc13ae0367fa21ee"
  },
  {
    "position": 5,
    "is_sold": true,
    "sold_to": {},
    "serial": "658c4b88fc13ae0367fa21ef"
  },
  {
    "position": 6,
    "is_sold": true,
    "sold_to": {},
    "serial": "658c4b88fc13ae0367fa21f0"
  },
  {
    "position": 7,
    "is_sold": true,
    "sold_to": {},
    "serial": "658c4b88fc13ae0367fa21f1"
  },
  {
    "position": 8,
    "is_sold": false,
    "sold_to": {},
    "serial": "658c4b88fc13ae0367fa21f2"
  },
  {
    "position": 9,
    "is_sold": false,
    "sold_to": {},
    "serial": "658c4b88fc13ae0367fa21f3"
  },
  {
    "position": 10,
    "is_sold": true,
    "sold_to": {},
    "serial": "658c4b88fc13ae0367fa21f4"
  },
  {
    "position": 11,
    "is_sold": false,
    "sold_to": {},
    "serial": "658c4b88fc13ae0367fa21f5"
  },
  {
    "position": 12,
    "is_sold": false,
    "sold_to": {},
    "serial": "658c4b88fc13ae0367fa21f6"
  },
  {
    "position": 13,
    "is_sold": true,
    "sold_to": {},
    "serial": "658c4b88fc13ae0367fa21f7"
  },
  {
    "position": 14,
    "is_sold": false,
    "sold_to": {},
    "serial": "658c4b88fc13ae0367fa21f8"
  },
  {
    "position": 15,
    "is_sold": true,
    "sold_to": {},
    "serial": "658c4b88fc13ae0367fa21f9"
  },
  {
    "position": 16,
    "is_sold": false,
    "sold_to": {},
    "serial": "658c4b88fc13ae0367fa21fa"
  },
  {
    "position": 17,
    "is_sold": true,
    "sold_to": {},
    "serial": "658c4b88fc13ae0367fa21fb"
  },
  {
    "position": 18,
    "is_sold": true,
    "sold_to": {},
    "serial": "658c4b88fc13ae0367fa21fc"
  },
  {
    "position": 19,
    "is_sold": false,
    "sold_to": {},
    "serial": "658c4b88fc13ae0367fa21fd"
  },
  {
    "position": 20,
    "is_sold": false,
    "sold_to": {},
    "serial": "658c4b88fc13ae0367fa21fe"
  },
  {
    "position": 21,
    "is_sold": false,
    "sold_to": {},
    "serial": "658c4b88fc13ae0367fa21ff"
  },
  {
    "position": 22,
    "is_sold": false,
    "sold_to": {},
    "serial": "658c4b88fc13ae0367fa2200"
  },
  {
    "position": 23,
    "is_sold": false,
    "sold_to": {},
    "serial": "658c4b88fc13ae0367fa2201"
  },
  {
    "position": 24,
    "is_sold": false,
    "sold_to": {},
    "serial": "658c4b88fc13ae0367fa2202"
  },
  {
    "position": 25,
    "is_sold": false,
    "sold_to": {},
    "serial": "658c4b88fc13ae0367fa2203"
  },
  {
    "position": 26,
    "is_sold": true,
    "sold_to": {},
    "serial": "658c4b88fc13ae0367fa2204"
  },
  {
    "position": 27,
    "is_sold": false,
    "sold_to": {},
    "serial": "658c4b88fc13ae0367fa2205"
  },
  {
    "position": 28,
    "is_sold": false,
    "sold_to": {},
    "serial": "658c4b88fc13ae0367fa2206"
  },
  {
    "position": 29,
    "is_sold": true,
    "sold_to": {},
    "serial": "658c4b88fc13ae0367fa2207"
  },
  {
    "position": 30,
    "is_sold": true,
    "sold_to": {},
    "serial": "658c4b88fc13ae0367fa2208"
  },
  {
    "position": 31,
    "is_sold": false,
    "sold_to": {},
    "serial": "658c4b88fc13ae0367fa2209"
  },
  {
    "position": 32,
    "is_sold": true,
    "sold_to": {},
    "serial": "658c4b88fc13ae0367fa220a"
  },
  {
    "position": 33,
    "is_sold": false,
    "sold_to": {},
    "serial": "658c4b88fc13ae0367fa220b"
  },
  {
    "position": 34,
    "is_sold": false,
    "sold_to": {},
    "serial": "658c4b88fc13ae0367fa220c"
  },
  {
    "position": 35,
    "is_sold": true,
    "sold_to": {},
    "serial": "658c4b88fc13ae0367fa220d"
  },
  {
    "position": 36,
    "is_sold": true,
    "sold_to": {},
    "serial": "658c4b88fc13ae0367fa220e"
  },
  {
    "position": 37,
    "is_sold": true,
    "sold_to": {},
    "serial": "658c4b88fc13ae0367fa220f"
  },
  {
    "position": 38,
    "is_sold": true,
    "sold_to": {},
    "serial": "658c4b88fc13ae0367fa2210"
  },
  {
    "position": 39,
    "is_sold": false,
    "sold_to": {},
    "serial": "658c4b88fc13ae0367fa2211"
  },
  {
    "position": 40,
    "is_sold": true,
    "sold_to": {},
    "serial": "658c4b88fc13ae0367fa2212"
  },
  {
    "position": 41,
    "is_sold": false,
    "sold_to": {},
    "serial": "658c4b88fc13ae0367fa2213"
  },
  {
    "position": 42,
    "is_sold": false,
    "sold_to": {},
    "serial": "658c4b88fc13ae0367fa2214"
  },
  {
    "position": 43,
    "is_sold": false,
    "sold_to": {},
    "serial": "658c4b88fc13ae0367fa2215"
  },
  {
    "position": 44,
    "is_sold": false,
    "sold_to": {},
    "serial": "658c4b88fc13ae0367fa2216"
  },
  {
    "position": 45,
    "is_sold": true,
    "sold_to": {},
    "serial": "658c4b88fc13ae0367fa2217"
  },
  {
    "position": 46,
    "is_sold": true,
    "sold_to": {},
    "serial": "658c4b88fc13ae0367fa2218"
  },
  {
    "position": 47,
    "is_sold": false,
    "sold_to": {},
    "serial": "658c4b88fc13ae0367fa2219"
  },
  {
    "position": 48,
    "is_sold": true,
    "sold_to": {},
    "serial": "658c4b88fc13ae0367fa221a"
  },
  {
    "position": 49,
    "is_sold": true,
    "sold_to": {},
    "serial": "658c4b88fc13ae0367fa221b"
  },
  {
    "position": 50,
    "is_sold": true,
    "sold_to": {},
    "serial": "658c4b88fc13ae0367fa221c"
  },
  {
    "position": 51,
    "is_sold": true,
    "sold_to": {},
    "serial": "658c4b88fc13ae0367fa221d"
  },
  {
    "position": 52,
    "is_sold": false,
    "sold_to": {},
    "serial": "658c4b88fc13ae0367fa221e"
  },
  {
    "position": 53,
    "is_sold": false,
    "sold_to": {},
    "serial": "658c4b88fc13ae0367fa221f"
  },
  {
    "position": 54,
    "is_sold": true,
    "sold_to": {},
    "serial": "658c4b88fc13ae0367fa2220"
  },
  {
    "position": 55,
    "is_sold": false,
    "sold_to": {},
    "serial": "658c4b88fc13ae0367fa2221"
  },
  {
    "position": 56,
    "is_sold": true,
    "sold_to": {},
    "serial": "658c4b88fc13ae0367fa2222"
  },
  {
    "position": 57,
    "is_sold": true,
    "sold_to": {},
    "serial": "658c4b88fc13ae0367fa2223"
  },
  {
    "position": 58,
    "is_sold": false,
    "sold_to": {},
    "serial": "658c4b88fc13ae0367fa2224"
  },
  {
    "position": 59,
    "is_sold": true,
    "sold_to": {},
    "serial": "658c4b88fc13ae0367fa2225"
  },
  {
    "position": 60,
    "is_sold": false,
    "sold_to": {},
    "serial": "658c4b88fc13ae0367fa2226"
  },
  {
    "position": 61,
    "is_sold": true,
    "sold_to": {},
    "serial": "658c4b88fc13ae0367fa2227"
  },
  {
    "position": 62,
    "is_sold": false,
    "sold_to": {},
    "serial": "658c4b88fc13ae0367fa2228"
  },
  {
    "position": 63,
    "is_sold": false,
    "sold_to": {},
    "serial": "658c4b88fc13ae0367fa2229"
  },
  {
    "position": 64,
    "is_sold": false,
    "sold_to": {},
    "serial": "658c4b88fc13ae0367fa222a"
  },
  {
    "position": 65,
    "is_sold": false,
    "sold_to": {},
    "serial": "658c4b88fc13ae0367fa222b"
  },
  {
    "position": 66,
    "is_sold": true,
    "sold_to": {},
    "serial": "658c4b88fc13ae0367fa222c"
  },
  {
    "position": 67,
    "is_sold": true,
    "sold_to": {},
    "serial": "658c4b88fc13ae0367fa222d"
  },
  {
    "position": 68,
    "is_sold": true,
    "sold_to": {},
    "serial": "658c4b88fc13ae0367fa222e"
  },
  {
    "position": 69,
    "is_sold": false,
    "sold_to": {},
    "serial": "658c4b88fc13ae0367fa222f"
  },
  {
    "position": 70,
    "is_sold": true,
    "sold_to": {},
    "serial": "658c4b88fc13ae0367fa2230"
  },
  {
    "position": 71,
    "is_sold": false,
    "sold_to": {},
    "serial": "658c4b88fc13ae0367fa2231"
  },
  {
    "position": 72,
    "is_sold": false,
    "sold_to": {},
    "serial": "658c4b88fc13ae0367fa2232"
  },
  {
    "position": 73,
    "is_sold": true,
    "sold_to": {},
    "serial": "658c4b88fc13ae0367fa2233"
  },
  {
    "position": 74,
    "is_sold": false,
    "sold_to": {},
    "serial": "658c4b88fc13ae0367fa2234"
  },
  {
    "position": 75,
    "is_sold": false,
    "sold_to": {},
    "serial": "658c4b88fc13ae0367fa2235"
  },
  {
    "position": 76,
    "is_sold": false,
    "sold_to": {},
    "serial": "658c4b88fc13ae0367fa2236"
  },
  {
    "position": 77,
    "is_sold": false,
    "sold_to": {},
    "serial": "658c4b88fc13ae0367fa2237"
  },
  {
    "position": 78,
    "is_sold": false,
    "sold_to": {},
    "serial": "658c4b88fc13ae0367fa2238"
  },
  {
    "position": 79,
    "is_sold": true,
    "sold_to": {},
    "serial": "658c4b88fc13ae0367fa2239"
  },
  {
    "position": 80,
    "is_sold": false,
    "sold_to": {},
    "serial": "658c4b88fc13ae0367fa223a"
  },
  {
    "position": 81,
    "is_sold": false,
    "sold_to": {},
    "serial": "658c4b88fc13ae0367fa223b"
  },
  {
    "position": 82,
    "is_sold": true,
    "sold_to": {},
    "serial": "658c4b88fc13ae0367fa223c"
  },
  {
    "position": 83,
    "is_sold": false,
    "sold_to": {},
    "serial": "658c4b88fc13ae0367fa223d"
  },
  {
    "position": 84,
    "is_sold": false,
    "sold_to": {},
    "serial": "658c4b88fc13ae0367fa223e"
  },
  {
    "position": 85,
    "is_sold": true,
    "sold_to": {},
    "serial": "658c4b88fc13ae0367fa223f"
  },
  {
    "position": 86,
    "is_sold": true,
    "sold_to": {},
    "serial": "658c4b88fc13ae0367fa2240"
  },
  {
    "position": 87,
    "is_sold": true,
    "sold_to": {},
    "serial": "658c4b88fc13ae0367fa2241"
  },
  {
    "position": 88,
    "is_sold": true,
    "sold_to": {},
    "serial": "658c4b88fc13ae0367fa2242"
  },
  {
    "position": 89,
    "is_sold": false,
    "sold_to": {},
    "serial": "658c4b88fc13ae0367fa2243"
  },
  {
    "position": 90,
    "is_sold": false,
    "sold_to": {},
    "serial": "658c4b88fc13ae0367fa2244"
  },
  {
    "position": 91,
    "is_sold": true,
    "sold_to": {},
    "serial": "658c4b88fc13ae0367fa2245"
  },
  {
    "position": 92,
    "is_sold": false,
    "sold_to": {},
    "serial": "658c4b88fc13ae0367fa2246"
  },
  {
    "position": 93,
    "is_sold": false,
    "sold_to": {},
    "serial": "658c4b88fc13ae0367fa2247"
  },
  {
    "position": 94,
    "is_sold": true,
    "sold_to": {},
    "serial": "658c4b88fc13ae0367fa2248"
  },
  {
    "position": 95,
    "is_sold": true,
    "sold_to": {},
    "serial": "658c4b88fc13ae0367fa2249"
  },
  {
    "position": 96,
    "is_sold": true,
    "sold_to": {},
    "serial": "658c4b88fc13ae0367fa224a"
  },
  {
    "position": 97,
    "is_sold": false,
    "sold_to": {},
    "serial": "658c4b88fc13ae0367fa224b"
  },
  {
    "position": 98,
    "is_sold": false,
    "sold_to": {},
    "serial": "658c4b88fc13ae0367fa224c"
  },
  {
    "position": 99,
    "is_sold": false,
    "sold_to": {},
    "serial": "658c4b88fc13ae0367fa224d"
  },
  {
    "position": 100,
    "is_sold": true,
    "sold_to": {},
    "serial": "658c4b88fc13ae0367fa224e"
  }
]
